Metadata-Version: 1.1
Name: python-amplitude-export
Version: 0.0.1
Summary: Python wrapper for Amplitude Export API
Home-page: https://github.com/MasiCal354/python-amplitude-export
Author: Faisal Malik Widya Prasetya
Author-email: faisalmalikwidyaprasetya@gmail.com
License: MIT
Download-URL: https://github.com/MasiCal354/python-amplitude-export/archive/v_01.tar.gz
Keywords: amplitude,export,api
Platform: UNKNOWN
Classifier: Development Status :: 3 - Alpha
Classifier: Intended Audience :: Developers
Classifier: Topic :: Software Development :: Build Tools
Classifier: License :: OSI Approved :: MIT License
Classifier: Programming Language :: Python :: 3
Classifier: Programming Language :: Python :: 3.4
Classifier: Programming Language :: Python :: 3.5
Classifier: Programming Language :: Python :: 3.6
Classifier: Programming Language :: Python :: 3.7
Classifier: Programming Language :: Python :: 3.8
Classifier: Programming Language :: Python :: 3.9
